{
    "url": "string",
    "source": ["BringATrailer"],
    "lot_number": "string",
    "seller": "string",
    "seller_type": ["Private Party", "Dealer"],
    "result": ["Sold", "Reserve Not Met"],
    "high_bidder": "string",
    "price": "integer",
    "sale_date": "datetime",
    "number_of_bids": "integer",
    "title": "string",
    "vin": "string",
    "year": "integer",
    "make": "string",
    "model": "string",
    "variant": "string",
    "convertible": "boolean",
    "engine": "string",
    "transmission": "string",
    "exterior_color": "string",
    "interior_color": "string",
    "mileage": "integer",
    "location": "string",
    "listing_details": "string[]",
    "excerpt": "string[]"
}